csbom.py
app/__init__.py
app/__main__.py
app/application.py
csbom-1.0.3.dist-info/LICENSE
csbom-1.0.3.dist-info/METADATA
csbom-1.0.3.dist-info/WHEEL
csbom-1.0.3.dist-info/entry_points.txt
csbom-1.0.3.dist-info/top_level.txt
csbom-1.0.3.dist-info/RECORD
